{
    "relationships": [
        {
            "relationshipId": 1,
            "relationshipName": "user",
            "relationshipNameCapitalized": "User",
            "relationshipFieldName": "user",
            "otherEntityName": "user",
            "relationshipType": "many-to-one",
            "otherEntityNameCapitalized": "User",
            "otherEntityField": "id"
        }
    ],
    "fields": [
        {
            "fieldId": 1,
            "fieldName": "url",
            "fieldType": "String",
            "fieldNameCapitalized": "Url",
            "fieldNameUnderscored": "url",
            "fieldInJavaBeanMethod": "Url",
            "fieldValidate": true,
            "fieldValidateRules": []
        },
        {
            "fieldId": 2,
            "fieldName": "thumbnailUrl",
            "fieldType": "String",
            "fieldNameCapitalized": "ThumbnailUrl",
            "fieldNameUnderscored": "thumbnail_url",
            "fieldInJavaBeanMethod": "ThumbnailUrl",
            "fieldValidate": true,
            "fieldValidateRules": []
        },
        {
            "fieldId": 3,
            "fieldName": "width",
            "fieldType": "Integer",
            "fieldNameCapitalized": "Width",
            "fieldNameUnderscored": "width",
            "fieldInJavaBeanMethod": "Width",
            "fieldValidate": false
        },
        {
            "fieldId": 4,
            "fieldName": "height",
            "fieldType": "Integer",
            "fieldNameCapitalized": "Height",
            "fieldNameUnderscored": "height",
            "fieldInJavaBeanMethod": "Height",
            "fieldValidate": false
        },
        {
            "fieldId": 5,
            "fieldName": "likes",
            "fieldType": "Integer",
            "fieldNameCapitalized": "Likes",
            "fieldNameUnderscored": "likes",
            "fieldInJavaBeanMethod": "Likes",
            "fieldValidate": false
        }
    ],
    "fieldsContainOwnerManyToMany": false,
    "fieldsContainOwnerOneToOne": false,
    "fieldsContainOneToMany": false,
    "fieldsContainLocalDate": false,
    "fieldsContainCustomTime": false,
    "fieldsContainBigDecimal": false,
    "fieldsContainDateTime": false,
    "fieldsContainDate": false,
    "changelogDate": "20160416102108",
    "dto": "no",
    "pagination": "pager",
    "validation": true
}